firebase/__init__.py
firebase/_custom_requests.py
firebase/_exception.py
firebase/_service_account_credentials.py
firebase/auth/__init__.py
firebase/database/__init__.py
firebase/database/_closable_sse_client.py
firebase/database/_custom_sse_client.py
firebase/database/_db_convert.py
firebase/database/_keep_auth_session.py
firebase/database/_stream.py
firebase/storage/__init__.py
firebase_rest_api-0.4.9.dist-info/LICENSE
firebase_rest_api-0.4.9.dist-info/WHEEL
firebase_rest_api-0.4.9.dist-info/METADATA
firebase_rest_api-0.4.9.dist-info/RECORD
