Metadata-Version: 2.1
Name: firebase-rest-api
Version: 0.4.9
Summary: A simple python wrapper for Google's Firebase REST API's.
Keywords: firebase,firebase-auth,firebase-database,firebase-realtime-database,firebase-storage
Author-email: Asif Arman Rahman <AsifArmanRahman@gmail.com>
Requires-Python: >=3.6
Classifier: Development Status :: 5 - Production/Stable
Classifier: Intended Audience :: Developers
Classifier: License :: OSI Approved :: MIT License
Classifier: Natural Language :: English
Classifier: Operating System :: OS Independent
Classifier: Programming Language :: Python
Classifier: Programming Language :: Python :: 3
Classifier: Programming Language :: Python :: 3.6
Classifier: Programming Language :: Python :: 3.7
Classifier: Programming Language :: Python :: 3.8
Classifier: Programming Language :: Python :: 3.9
Classifier: Programming Language :: Python :: 3.10
Classifier: Topic :: Software Development :: Libraries :: Python Modules
Requires-Dist: gcloud>=0.18.3
Requires-Dist: oauth2client>=4.1.3
Requires-Dist: python_jwt>=3.3.2
Requires-Dist: requests>=2.27.1
Requires-Dist: six>=1.16.0
Requires-Dist: Sphinx>=5.0.2 ; extra == "docs"
Requires-Dist: sphinx-rtd-theme>=1.0.0 ; extra == "docs"
Requires-Dist: sphinx_design>=0.2.0 ; extra == "docs"
Requires-Dist: toml>=0.10.2 ; extra == "docs"
Project-URL: Documentation, https://firebase-rest-api.readthedocs.io/
Project-URL: Source, https://github.com/AsifArmanRahman/firebase-rest-api
Provides-Extra: docs
